{
    "dependencies": [
        {
            "name": "kubernetes-mixin",
            "source": {
                "git": {
                    "remote": "https://github.com/kubernetes-monitoring/kubernetes-mixin",
                    "subdir": ""
                }
            },
            "version": "master"
        },
        {
            "name": "prometheus-mixin",
            "source": {
                "git": {
                    "remote": "https://github.com/prometheus/prometheus",
                    "subdir": "documentation/prometheus-mixin"
                }
            },
            "version": "master"
        },
        {
            "name": "alertmanager-mixin",
            "source": {
                "git": {
                    "remote": "https://github.com/prometheus/alertmanager",
                    "subdir": "doc/alertmanager-mixin"
                }
            },
            "version": "mixin"
        },
        {
            "name": "node-mixin",
            "source": {
                "git": {
                    "remote": "https://github.com/prometheus/node_exporter",
                    "subdir": "docs/node-mixin"
                }
            },
            "version": "master"
        },
        {
            "name": "oauth2_proxy",
            "source": {
                "git": {
                    "remote": "https://github.com/grafana/jsonnet-libs",
                    "subdir": "oauth2-proxy"
                }
            },
            "version": "master"
        },
        {
            "name": "ksonnet-util",
            "source": {
                "git": {
                    "remote": "https://github.com/grafana/jsonnet-libs",
                    "subdir": "ksonnet-util"
                }
            },
            "version": "master"
        }
    ]
}
